svo_filters/__init__.py
svo_filters/setup_package.py
svo_filters/svo.py
svo_filters/test_svo.py
svo_filters/utils.py
svo_filters/data/.DS_Store
svo_filters/data/filters/.DS_Store
svo_filters/data/filters/.gitkeep
svo_filters/data/filters/2MASS.H
svo_filters/data/filters/2MASS.J
svo_filters/data/filters/2MASS.Ks
svo_filters/data/filters/ACS_HRC.F435W
svo_filters/data/filters/ACS_HRC.F555W
svo_filters/data/filters/ACS_HRC.F658N
svo_filters/data/filters/ACS_HRC.F775W
svo_filters/data/filters/ACS_HRC.F850LP
svo_filters/data/filters/Cousins.I
svo_filters/data/filters/Cousins.R
svo_filters/data/filters/FourStar.J
svo_filters/data/filters/FourStar.J1
svo_filters/data/filters/FourStar.J2
svo_filters/data/filters/FourStar.J3
svo_filters/data/filters/GALEX.FUV
svo_filters/data/filters/GALEX.NUV
svo_filters/data/filters/Gaia.G
svo_filters/data/filters/Gaia.bp
svo_filters/data/filters/Gaia.rp
svo_filters/data/filters/HAWK_I.H.txt
svo_filters/data/filters/HAWK_I.J.txt
svo_filters/data/filters/HAWK_I.Ks.txt
svo_filters/data/filters/IRAC.I1
svo_filters/data/filters/IRAC.I2
svo_filters/data/filters/IRAC.I3
svo_filters/data/filters/IRAC.I4
svo_filters/data/filters/Johnson.V
svo_filters/data/filters/Kepler.K
svo_filters/data/filters/MIRI.F1000W
svo_filters/data/filters/MIRI.F1130W
svo_filters/data/filters/MIRI.F1280W
svo_filters/data/filters/MIRI.F1500W
svo_filters/data/filters/MIRI.F1800W
svo_filters/data/filters/MIRI.F2100W
svo_filters/data/filters/MIRI.F2550W
svo_filters/data/filters/MIRI.F560W
svo_filters/data/filters/MIRI.F770W
svo_filters/data/filters/NICMOS3.F110W
svo_filters/data/filters/NICMOS3.F160W
svo_filters/data/filters/NIRCam.F070W
svo_filters/data/filters/NIRCam.F090W
svo_filters/data/filters/NIRCam.F115W
svo_filters/data/filters/NIRCam.F140M
svo_filters/data/filters/NIRCam.F150W
svo_filters/data/filters/NIRCam.F150W2
svo_filters/data/filters/NIRCam.F162M
svo_filters/data/filters/NIRCam.F164N
svo_filters/data/filters/NIRCam.F182M
svo_filters/data/filters/NIRCam.F187N
svo_filters-0.5.2.dist-info/licenses/LICENSE
svo_filters-0.5.2.dist-info/METADATA
svo_filters-0.5.2.dist-info/WHEEL
svo_filters-0.5.2.dist-info/dependency_links.txt
svo_filters-0.5.2.dist-info/top_level.txt
svo_filters-0.5.2.dist-info/zip-safe
svo_filters-0.5.2.dist-info/RECORD
