Metadata-Version: 2.4
Name: svo_filters
Version: 0.5.2
Summary: A Python wrapper for the SVO Filter Profile Service
Home-page: https://github.com/hover2pi/svo_filters
Author: Joe Filippazzo
Author-email: jfilippazzo@stsci.edu
License: MIT
License-File: LICENSE
Requires-Dist: astropy
Requires-Dist: bokeh
Requires-Dist: ipython
Requires-Dist: matplotlib
Requires-Dist: numpy
Requires-Dist: numpydoc
Requires-Dist: pytest
Requires-Dist: pyyaml
Dynamic: author
Dynamic: author-email
Dynamic: home-page
Dynamic: license
Dynamic: license-file
Dynamic: requires-dist
Dynamic: summary
